fxpoppet/__init__.py
fxpoppet/__main__.py
fxpoppet/adb_process.py
fxpoppet/adb_session.py
fxpoppet/main.py
fxpoppet/py.typed
fxpoppet/test_adb_process.py
fxpoppet/test_adb_session.py
fxpoppet/test_main.py
fxpoppet/emulator/android.py
fxpoppet-0.3.5.dist-info/licenses/LICENSE
fxpoppet-0.3.5.dist-info/METADATA
fxpoppet-0.3.5.dist-info/WHEEL
fxpoppet-0.3.5.dist-info/entry_points.txt
fxpoppet-0.3.5.dist-info/top_level.txt
fxpoppet-0.3.5.dist-info/RECORD
