Metadata-Version: 2.4
Name: fxpoppet
Version: 0.3.5
Summary: A Python module that enables the automation of Firefox on Android
Home-page: https://github.com/MozillaSecurity/fxpoppet
Author: Tyson Smith
Author-email: twsmith@mozilla.com
Maintainer: Mozilla Fuzzing Team
Maintainer-email: fuzzing@mozilla.com
License: MPL 2.0
Keywords: automation testing
Classifier: Intended Audience :: Developers
Classifier: License :: OSI Approved :: Mozilla Public License 2.0 (MPL 2.0)
Classifier: Programming Language :: Python :: 3
Classifier: Topic :: Software Development :: Testing
Requires-Python: >=3.9
License-File: LICENSE
Requires-Dist: ffpuppet>=0.16.0
Requires-Dist: fuzzfetch
Requires-Dist: PyYAML
Requires-Dist: xvfbwrapper
Provides-Extra: dev
Requires-Dist: pre-commit; extra == "dev"
Requires-Dist: tox; extra == "dev"
Dynamic: license-file
